displayFlips/Formatage.py
displayFlips/__init__.py
displayFlips/triangulationDisplay.py
displayFlips/JS/Main.js
displayFlips/JS/config.js
displayFlips/JS/graph.js
displayFlips/JS/line.js
displayFlips/JS/model.js
displayFlips/JS/triangle.js
displayFlips-0.1.1.3.dist-info/METADATA
displayFlips-0.1.1.3.dist-info/WHEEL
displayFlips-0.1.1.3.dist-info/top_level.txt
displayFlips-0.1.1.3.dist-info/RECORD
