Metadata-Version: 2.1
Name: displayFlips
Version: 0.1.1.3
Summary: A python module using Veerer for drawing flat structures of triangulations in Jupyter Notebook
Home-page: UNKNOWN
Author: UNKNOWN
Author-email: UNKNOWN
License: UNKNOWN
Platform: UNKNOWN
